{
  "imports" : [
    "KeychainAccess",
    "PromiseKit",
    "PMKFoundation",
    "PMKStoreKit",
    "SortedArray",
    "LegibleError"
  ],
  "modules" : [
    {
      "path" : "",
      "swiftVersion" : "4",
      "files" : [
        "mxcl∕KeychainAccess.swift"
      ],
      "name" : "KeychainAccess",
      "dependencies" : [

      ]
    },
    {
      "path" : "",
      "swiftVersion" : "5.0",
      "files" : [
        "mxcl∕LegibleError-1.0.1.swift"
      ],
      "name" : "LegibleError",
      "dependencies" : [

      ]
    },
    {
      "path" : "mxcl∕PromiseKit-6.8.3",
      "swiftVersion" : "5.0",
      "files" : [
        "after.swift",
        "Box.swift",
        "Catchable.swift",
        "Configuration.swift",
        "CustomStringConvertible.swift",
        "Error.swift",
        "firstly.swift",
        "Guarantee.swift",
        "hang.swift",
        "LogEvent.swift",
        "Promise.swift",
        "race.swift",
        "Resolver.swift",
        "Thenable.swift",
        "when.swift"
      ],
      "name" : "PromiseKit",
      "dependencies" : [

      ]
    },
    {
      "path" : "PromiseKit∕Foundation-3.3.1",
      "swiftVersion" : "5.0",
      "files" : [
        "afterlife.swift",
        "NSNotificationCenter+Promise.swift",
        "NSObject+Promise.swift",
        "NSURLSession+Promise.swift",
        "Process+Promise.swift"
      ],
      "name" : "PMKFoundation",
      "dependencies" : [
        "PromiseKit"
      ]
    },
    {
      "path" : "PromiseKit∕StoreKit-3.1.1",
      "swiftVersion" : "4.2",
      "files" : [
        "SKPayment+Promise.swift",
        "SKPaymentQueue+Promise.swift",
        "SKProductsRequest+Promise.swift",
        "SKReceiptRefreshRequest+Promise.swift"
      ],
      "name" : "PMKStoreKit",
      "dependencies" : [
        "PromiseKit"
      ]
    },
    {
      "path" : "",
      "swiftVersion" : "4",
      "files" : [
        "ole∕SortedArray-0.7.0.swift"
      ],
      "name" : "SortedArray",
      "dependencies" : [

      ]
    }
  ],
  "packages" : [
    {
      "name" : "mxcl\/KeychainAccess",
      "path" : "..\/.cake\/swift-pm\/checkouts\/KeychainAccess",
      "moduleNames" : [
        "KeychainAccess"
      ]
    },
    {
      "path" : "..\/.cake\/swift-pm\/checkouts\/PromiseKit",
      "moduleNames" : [
        "PromiseKit"
      ],
      "name" : "mxcl\/PromiseKit",
      "version" : "6.8.3"
    },
    {
      "path" : "..\/.cake\/swift-pm\/checkouts\/LegibleError",
      "moduleNames" : [
        "LegibleError"
      ],
      "name" : "mxcl\/LegibleError",
      "version" : "1.0.1"
    },
    {
      "path" : "..\/.cake\/swift-pm\/checkouts\/SortedArray",
      "moduleNames" : [
        "SortedArray"
      ],
      "name" : "ole\/SortedArray",
      "version" : "0.7.0"
    },
    {
      "path" : "..\/.cake\/swift-pm\/checkouts\/Foundation",
      "moduleNames" : [
        "PMKFoundation"
      ],
      "name" : "PromiseKit\/Foundation",
      "version" : "3.3.1"
    },
    {
      "path" : "..\/.cake\/swift-pm\/checkouts\/StoreKit",
      "moduleNames" : [
        "PMKStoreKit"
      ],
      "name" : "PromiseKit\/StoreKit",
      "version" : "3.1.1"
    }
  ]
}